odoo/addons/helpdesk_mgmt/README.rst
odoo/addons/helpdesk_mgmt/__init__.py
odoo/addons/helpdesk_mgmt/__manifest__.py
odoo/addons/helpdesk_mgmt/controllers/__init__.py
odoo/addons/helpdesk_mgmt/controllers/main.py
odoo/addons/helpdesk_mgmt/controllers/myaccount.py
odoo/addons/helpdesk_mgmt/data/helpdesk_data.xml
odoo/addons/helpdesk_mgmt/demo/helpdesk_demo.xml
odoo/addons/helpdesk_mgmt/i18n/ca.po
odoo/addons/helpdesk_mgmt/i18n/ca_ES.po
odoo/addons/helpdesk_mgmt/i18n/de.po
odoo/addons/helpdesk_mgmt/i18n/de_AT.po
odoo/addons/helpdesk_mgmt/i18n/es.po
odoo/addons/helpdesk_mgmt/i18n/es_AR.po
odoo/addons/helpdesk_mgmt/i18n/es_CL.po
odoo/addons/helpdesk_mgmt/i18n/eu_ES.po
odoo/addons/helpdesk_mgmt/i18n/fr.po
odoo/addons/helpdesk_mgmt/i18n/helpdesk_mgmt.pot
odoo/addons/helpdesk_mgmt/i18n/hu.po
odoo/addons/helpdesk_mgmt/i18n/it.po
odoo/addons/helpdesk_mgmt/i18n/pt.po
odoo/addons/helpdesk_mgmt/i18n/pt_BR.po
odoo/addons/helpdesk_mgmt/i18n/sl.po
odoo/addons/helpdesk_mgmt/migrations/12.0.1.14.1/post-migrate.py
odoo/addons/helpdesk_mgmt/migrations/12.0.1.23.1/pre-migrate.py
odoo/addons/helpdesk_mgmt/models/__init__.py
odoo/addons/helpdesk_mgmt/models/helpdesk_ticket.py
odoo/addons/helpdesk_mgmt/models/helpdesk_ticket_category.py
odoo/addons/helpdesk_mgmt/models/helpdesk_ticket_channel.py
odoo/addons/helpdesk_mgmt/models/helpdesk_ticket_stage.py
odoo/addons/helpdesk_mgmt/models/helpdesk_ticket_tag.py
odoo/addons/helpdesk_mgmt/models/helpdesk_ticket_team.py
odoo/addons/helpdesk_mgmt/models/ir_attachment.py
odoo/addons/helpdesk_mgmt/models/res_partner.py
odoo/addons/helpdesk_mgmt/readme/CONFIGURE.rst
odoo/addons/helpdesk_mgmt/readme/CONTRIBUTORS.rst
odoo/addons/helpdesk_mgmt/readme/DESCRIPTION.rst
odoo/addons/helpdesk_mgmt/readme/USAGE.rst
odoo/addons/helpdesk_mgmt/security/helpdesk_security.xml
odoo/addons/helpdesk_mgmt/security/ir.model.access.csv
odoo/addons/helpdesk_mgmt/static/description/Categories.PNG
odoo/addons/helpdesk_mgmt/static/description/Channels.PNG
odoo12_addon_helpdesk_mgmt-12.0.1.26.0.dist-info/METADATA
odoo12_addon_helpdesk_mgmt-12.0.1.26.0.dist-info/WHEEL
odoo12_addon_helpdesk_mgmt-12.0.1.26.0.dist-info/top_level.txt
odoo12_addon_helpdesk_mgmt-12.0.1.26.0.dist-info/RECORD
