Metadata-Version: 2.1
Name: odoo12-addon-helpdesk-mgmt
Version: 12.0.1.26.0
Summary: Helpdesk
Home-page: https://github.com/OCA/helpdesk
Author: AdaptiveCity, C2i Change 2 Improve, Domatix, Factor Libre, SDi Soluciones, Odoo Community Association (OCA)
Author-email: support@odoo-community.org
License: AGPL-3
Platform: UNKNOWN
Classifier: Programming Language :: Python
Classifier: Framework :: Odoo
Classifier: Framework :: Odoo :: 12.0
Classifier: License :: OSI Approved :: GNU Affero General Public License v3
Classifier: Development Status :: 4 - Beta
Requires-Python: >=3.5
Requires-Dist: odoo (<12.1dev,>=12.0a)
